ciotemplate/CHANGELOG.md
ciotemplate/LICENSE
ciotemplate/README.md
ciotemplate/VERSION
ciotemplate/__init__.py
ciotemplate/expander.py
ciotemplate-0.1.2.dist-info/LICENSE
ciotemplate-0.1.2.dist-info/METADATA
ciotemplate-0.1.2.dist-info/WHEEL
ciotemplate-0.1.2.dist-info/top_level.txt
ciotemplate-0.1.2.dist-info/RECORD
