Metadata-Version: 2.1
Name: ciotemplate
Version: 0.1.2
Summary: Angle bracket template expansion
Home-page: https://github.com/AtomicConductor/ciotemplate
Author: conductor
Author-email: info@conductortech.com
License: UNKNOWN
Platform: UNKNOWN
Classifier: Operating System :: OS Independent
Classifier: Programming Language :: Python
Classifier: Topic :: Multimedia :: Graphics :: 3D Rendering
Requires-Dist: future (>=0.18.2)
